algotrading_core/__init__.py
algotrading_core/features/__init__.py
algotrading_core/features/aggregated.py
algotrading_core/features/base.py
algotrading_core/features/levels.py
algotrading_core/features/time_features.py
algotrading_core/features/volatility.py
algotrading_core/preprocessing/__init__.py
algotrading_core/preprocessing/adjustments.py
algotrading_core/preprocessing/candles.py
algotrading_core/preprocessing/transformers.py
algotrading_core/schemas/__init__.py
algotrading_core/schemas/candle.py
algotrading_core/schemas/feature.py
algotrading_core/schemas/model.py
algotrading_core/utils/__init__.py
algotrading_core/utils/datetime_utils.py
algotrading_core/utils/path_utils.py
algotrading_core/utils/setup_logger.py
algotrading_core-0.1.1.dist-info/METADATA
algotrading_core-0.1.1.dist-info/WHEEL
algotrading_core-0.1.1.dist-info/RECORD
