Metadata-Version: 2.4
Name: algotrading-core
Version: 0.1.1
Summary: Shared core package: schemas, preprocessing, features, and utils for the algorithmic trading platform
Requires-Python: <4,>=3.11
Requires-Dist: numpy<3,>=1.24
Requires-Dist: pandas<3,>=2.0
Requires-Dist: pydantic<3,>=2.0
Requires-Dist: pyyaml<7,>=6.0
